laceworkreports/__init__.py
laceworkreports/__main__.py
laceworkreports/cli/ExportHandlers/ActivitiesHandler/Activities.py
laceworkreports/cli/ExportHandlers/ConfigsHandler/Configs.py
laceworkreports/cli/ExportHandlers/DataExportHandlers/ConfigsAPIv2Handler.py
laceworkreports/cli/ExportHandlers/DataExportHandlers/GenericAPIv2Handler.py
laceworkreports/cli/ExportHandlers/DataExportHandlers/GenericExport.py
laceworkreports/cli/ExportHandlers/DataExportHandlers/GenericLQLHandler.py
laceworkreports/cli/ExportHandlers/DataExportHandlers/OptionValidator.py
laceworkreports/cli/ExportHandlers/EntitiesHandler/Entities.py
laceworkreports/cli/ExportHandlers/Export.py
laceworkreports/cli/ExportHandlers/QueriesHandler/Queries.py
laceworkreports/cli/ExportHandlers/VulnerabilitiesHandler/Vulnerabilities.py
laceworkreports/cli/ReportHandlers/AgentCoverageHandler/AgentCoverageHandler.py
laceworkreports/cli/ReportHandlers/AgentCoverageHandler/agent_coverage.html.j2
laceworkreports/cli/ReportHandlers/ComplianceCoverageHandler/ComplianceCoverageHandler.py
laceworkreports/cli/ReportHandlers/ComplianceCoverageHandler/compliance_coverage.html.j2
laceworkreports/cli/ReportHandlers/ContainerIntegrationCoverageHandler/ContainerIntegrationCoverageHandler.py
laceworkreports/cli/ReportHandlers/ContainerIntegrationCoverageHandler/container_integration_coverage.html.j2
laceworkreports/cli/ReportHandlers/ContainerVulnerabilityCoverageHandler/ContainerVulnerabilityCoverageHandler.py
laceworkreports/cli/ReportHandlers/ContainerVulnerabilityCoverageHandler/container_vulnerability_coverage.html.j2
laceworkreports/cli/ReportHandlers/InventoryCoverageHandler/InventoryCoverageHandler.py
laceworkreports/cli/ReportHandlers/InventoryCoverageHandler/inventory_coverage.html.j2
laceworkreports/cli/ReportHandlers/Report.py
laceworkreports/cli/ReportHandlers/VpcChartHandler/VpcChartHandler.py
laceworkreports/cli/ReportHandlers/VpcChartHandler/VpcChartHelper.py
laceworkreports-1.3.48.dist-info/entry_points.txt
laceworkreports-1.3.48.dist-info/LICENSE
laceworkreports-1.3.48.dist-info/WHEEL
laceworkreports-1.3.48.dist-info/METADATA
laceworkreports-1.3.48.dist-info/RECORD
