Metadata-Version: 2.1
Name: laceworkreports
Version: 1.3.48
Summary: laceworkreports is a Python cli/package for creating reports from Lacework data.
Home-page: https://github.com/laceworkps/laceworkreports
License: BSD-3
Author: Lacework Inc.
Author-email: jamie.mcmurray@lacework.net
Requires-Python: >=3.8,<4.0
Classifier: Development Status :: 3 - Alpha
Classifier: Intended Audience :: Developers
Classifier: License :: OSI Approved :: BSD License
Classifier: License :: Other/Proprietary License
Classifier: Operating System :: OS Independent
Classifier: Programming Language :: Python :: 3
Classifier: Programming Language :: Python :: 3.8
Classifier: Programming Language :: Python :: 3.9
Classifier: Programming Language :: Python :: 3.10
Classifier: Programming Language :: Python :: 3.11
Classifier: Programming Language :: Python :: 3
Classifier: Programming Language :: Python :: 3.10
Classifier: Programming Language :: Python :: 3.8
Classifier: Programming Language :: Python :: 3.9
Classifier: Topic :: Software Development :: Libraries :: Python Modules
Requires-Dist: Jinja2 (>=3.0.3,<4.0.0)
Requires-Dist: SQLAlchemy (>=1.4.32,<2.0.0)
Requires-Dist: SQLAlchemy-Utils (>=0.38.2,<0.39.0)
Requires-Dist: anaconda (>=0.0.1,<0.0.2)
Requires-Dist: click (==8.0.4)
Requires-Dist: importlib-metadata (>=4.10.1,<5.0.0)
Requires-Dist: importlib_metadata (>=4.5.0,<5.0.0); python_version < "3.8"
Requires-Dist: laceworksdk (>=1.1.0,<2.0.0)
Requires-Dist: matplotlib (>=3.5.1,<4.0.0)
Requires-Dist: networkx (>=2.8,<3.0)
Requires-Dist: pandas (>=1.4.1,<2.0.0)
Requires-Dist: psycopg2-binary (>=2.9.3,<3.0.0)
Requires-Dist: rich (>=10.14,<13.0)
Requires-Dist: scipy (>=1.8.0,<2.0.0); python_version >= "3.8" and python_version < "3.11"
Requires-Dist: typer[all] (>=0.4.0,<0.5.0)
Project-URL: Repository, https://github.com/laceworkps/laceworkreports
